{
  "timezone": "America/Argentina/Buenos_Aires",
  "profiles": {
    "day": {
      "startHour": 6,
      "endHour": 24,
      "intervalMinutes": 15
    },
    "night": {
      "startHour": 0,
      "endHour": 6,
      "intervalMinutes": 120
    }
  },
  "windows": [
    {
      "id": "2026-1c-main",
      "label": "Inscripción materias 1C (principal)",
      "start": "2026-03-12T00:00:00-03:00",
      "end": "2026-03-17T23:59:59-03:00",
      "enabled": true
    },
    {
      "id": "2026-1c-supplementary",
      "label": "Inscripción materias 1C (suplementaria)",
      "start": "2026-03-23T00:00:00-03:00",
      "end": "2026-03-26T23:59:59-03:00",
      "enabled": true
    },
    {
      "id": "2026-2c-main",
      "label": "Inscripción materias 2C (principal)",
      "start": "2026-07-30T00:00:00-03:00",
      "end": "2026-08-04T23:59:59-03:00",
      "enabled": true
    },
    {
      "id": "2026-2c-supplementary",
      "label": "Inscripción materias 2C (suplementaria)",
      "start": "2026-08-08T00:00:00-03:00",
      "end": "2026-08-11T23:59:59-03:00",
      "enabled": true
    }
  ],
  "updatedAt": "2026-03-14T00:00:00.000Z"
}
