{
  "id": "25-teoria-y-tecnica-de-exploracion-y-diagnostico-psicologico-modulo-i-c59-i",
  "label": "(25) Teoría y Técnica de Exploración y Diagnóstico Psicológico Módulo I - Cátedra 59 (I)",
  "header": "Psicología UBA - Licenciatura en Psicología - (25) Teoría y Técnica de Exploración y Diagnóstico Psicológico Módulo I - Cátedra 59 - I - Mikulic",
  "teoricos": [
    "I|lunes|09:15|10:45|Radusky, David Pablo|IN-510|",
    "II|lunes|18:00|19:30|Crespi, Melina Claudia|IN-MAY|",
    "III|martes|15:00|16:45|Cassullo, Gabriela Livia|SI-027|San Isidro",
    "IV|miercoles|11:00|12:30|Mikulic, Isabel Maria|HY-005|"
  ],
  "seminarios": [],
  "comisiones": [
    "1|lunes|11:00|14:15|Giardina, Eliana|I|IN-451|",
    "2|lunes|14:30|17:45|Cubas Gonzalez, Elizabeth|II|IN-211|",
    "3|lunes|19:45|23:00|Gallardo, Fabio|II|IN-208|",
    "4|miercoles|07:30|10:45|Stella, Fernando|IV|HY-015|",
    "5|miercoles|12:45|16:00|Aboy, Sabrina|IV|IN-207|",
    "6|sabado|09:15|12:30|Torres, Ramiro Ignacio|II|IN-430|",
    "7|lunes|14:30|17:45|Laguna, Sofia|II|IN-216|",
    "8|lunes|19:45|23:00|Prieto, Fernando|II|IN-124|",
    "9|lunes|14:30|17:45|Lastra, Andrea Soledad|II|IN-205|",
    "10|miercoles|12:45|16:00|Salgado Salinas, Lorena|IV|HY-004|",
    "11|miercoles|07:30|10:45|Mancini, Natalia|IV|HY-012|",
    "12|lunes|11:00|14:15|Deleersnyder, Guido|I|IN-430|",
    "13|jueves|11:00|14:15|Paolo, Ana Maria|I|IN-213|",
    "14|lunes|11:00|14:15|Perez Martinez, Maria Jose|I|IN-420|",
    "15|miercoles|18:00|21:15|Pierri, Jesica Soledad|II|IN-434|",
    "16|viernes|18:00|21:15|Ogando, Julieta|II|IN-440|",
    "17|martes|18:00|21:15|Garcia Juarros, Maria Laura|II|IN-443|",
    "18|lunes|19:45|23:00|Del Río, Belén|II|IN-125|",
    "19|miercoles|12:45|16:00|Rein, Yasmin Iara|IV|HY-032|",
    "20|miercoles|07:30|10:45|Gramajo, Mauricio|IV|IN-123|",
    "50|martes|11:00|14:30|Borrego Maturana, Maria Floren|III|SI-025|"
  ]
}
