{
  "schemaVersion": 2,
  "id": "informatica-educacion-y-sociedad-c660",
  "label": "Informática, Educación y Sociedad - Cátedra 660",
  "header": "Psicología UBA - Licenciatura en Psicología - Informática, Educación y Sociedad - Cátedra 660 - Prof. Fernandez Zalazar",
  "slots": [
    {
      "id": "I",
      "dia": "martes",
      "inicio": "18:00",
      "fin": "19:30",
      "profesor": "Fernandez Zalazar, Diana Conce",
      "lugar": {
        "anexo": "HY",
        "aula": "030"
      },
      "tipo": "teo"
    },
    {
      "id": "II",
      "dia": "miercoles",
      "inicio": "11:00",
      "fin": "12:30",
      "profesor": "Jofre, Cristian",
      "lugar": {
        "anexo": "HY",
        "aula": "029"
      },
      "tipo": "teo"
    },
    {
      "id": "6",
      "dia": "martes",
      "inicio": "16:15",
      "fin": "17:45",
      "profesor": "Alvarez Sobrado, Emanuel",
      "lugar": {
        "anexo": "HY",
        "aula": "030"
      },
      "tipo": "prac",
      "vacantes": 0,
      "slotsAsociados": [
        {
          "slotId": "I",
          "rol": "teo",
          "condicion": "obligatorio"
        }
      ]
    },
    {
      "id": "1",
      "dia": "martes",
      "inicio": "19:45",
      "fin": "21:15",
      "profesor": "Borenzstein, Karen",
      "lugar": {
        "anexo": "HY",
        "aula": "024"
      },
      "tipo": "prac",
      "vacantes": 0,
      "slotsAsociados": [
        {
          "slotId": "I",
          "rol": "teo",
          "condicion": "obligatorio"
        }
      ]
    },
    {
      "id": "2",
      "dia": "martes",
      "inicio": "19:45",
      "fin": "21:15",
      "profesor": "Alvarez Sobrado, Emanuel",
      "lugar": {
        "anexo": "HY",
        "aula": "010"
      },
      "tipo": "prac",
      "vacantes": 5,
      "slotsAsociados": [
        {
          "slotId": "I",
          "rol": "teo",
          "condicion": "obligatorio"
        }
      ]
    },
    {
      "id": "3",
      "dia": "miercoles",
      "inicio": "09:15",
      "fin": "10:45",
      "profesor": "Gomez Korol, Dahian Ezequiel",
      "lugar": {
        "anexo": "HY",
        "aula": "024"
      },
      "tipo": "prac",
      "vacantes": 15,
      "slotsAsociados": [
        {
          "slotId": "II",
          "rol": "teo",
          "condicion": "obligatorio"
        }
      ]
    },
    {
      "id": "5",
      "dia": "miercoles",
      "inicio": "09:15",
      "fin": "10:45",
      "profesor": "Borenzstein, Karen",
      "lugar": {
        "anexo": "HY",
        "aula": "027"
      },
      "tipo": "prac",
      "vacantes": 18,
      "slotsAsociados": [
        {
          "slotId": "II",
          "rol": "teo",
          "condicion": "obligatorio"
        }
      ]
    },
    {
      "id": "4",
      "dia": "miercoles",
      "inicio": "12:45",
      "fin": "14:15",
      "profesor": "Gomez Korol, Dahian Ezequiel",
      "lugar": {
        "anexo": "HY",
        "aula": "024"
      },
      "tipo": "prac",
      "vacantes": 19,
      "slotsAsociados": [
        {
          "slotId": "II",
          "rol": "teo",
          "condicion": "obligatorio"
        }
      ]
    }
  ]
}
